[ {
  "demand" : 0,
  "workerAssignments" : [ {
    "t" : 0,
    "workers" : [ 10, 56, 249, 234 ]
  }, {
    "t" : 2,
    "workers" : [ 10, 56, 249, 234 ]
  }, {
    "t" : 3,
    "workers" : [ 10, 56, 249, 234 ]
  }, {
    "t" : 5,
    "workers" : [ 10, 56, 249, 234 ]
  }, {
    "t" : 6,
    "workers" : [ 10, 56, 249, 234 ]
  }, {
    "t" : 8,
    "workers" : [ 10, 56, 249, 234 ]
  }, {
    "t" : 9,
    "workers" : [ 10, 56, 249, 234 ]
  } ]
}, {
  "demand" : 1,
  "workerAssignments" : [ {
    "t" : 0,
    "workers" : [ 247, 142, 157 ]
  }, {
    "t" : 1,
    "workers" : [ 249, 247, 10 ]
  }, {
    "t" : 2,
    "workers" : [ 247, 142, 157 ]
  }, {
    "t" : 5,
    "workers" : [ 247, 142, 157 ]
  }, {
    "t" : 6,
    "workers" : [ 247, 142, 157 ]
  }, {
    "t" : 7,
    "workers" : [ 249, 247, 10 ]
  }, {
    "t" : 9,
    "workers" : [ 247, 142, 157 ]
  } ]
}, {
  "demand" : 2,
  "workerAssignments" : [ {
    "t" : 1,
    "workers" : [ 69, 88, 56 ]
  }, {
    "t" : 4,
    "workers" : [ 69, 249, 88 ]
  }, {
    "t" : 5,
    "workers" : [ 69, 88, 52 ]
  }, {
    "t" : 7,
    "workers" : [ 69, 88, 56 ]
  } ]
}, {
  "demand" : 3,
  "workerAssignments" : [ {
    "t" : 0,
    "workers" : [ 0, 5, 42, 288, 78, 216 ]
  }, {
    "t" : 2,
    "workers" : [ 0, 5, 42, 288, 78, 216 ]
  }, {
    "t" : 3,
    "workers" : [ 0, 5, 247, 42, 288, 78 ]
  }, {
    "t" : 4,
    "workers" : [ 0, 5, 247, 10, 56, 42 ]
  }, {
    "t" : 7,
    "workers" : [ 0, 5, 42, 288, 78, 216 ]
  }, {
    "t" : 8,
    "workers" : [ 0, 5, 247, 42, 288, 78 ]
  }, {
    "t" : 9,
    "workers" : [ 0, 5, 42, 288, 78, 216 ]
  } ]
}, {
  "demand" : 4,
  "workerAssignments" : [ {
    "t" : 2,
    "workers" : [ 69, 88, 269, 52, 238 ]
  }, {
    "t" : 4,
    "workers" : [ 269, 52, 157, 78, 216 ]
  }, {
    "t" : 5,
    "workers" : [ 269, 42, 78, 216, 238 ]
  }, {
    "t" : 7,
    "workers" : [ 269, 52, 157, 238, 74 ]
  }, {
    "t" : 8,
    "workers" : [ 69, 88, 269, 52, 157 ]
  } ]
}, {
  "demand" : 5,
  "workerAssignments" : [ {
    "t" : 1,
    "workers" : [ 142, 52 ]
  }, {
    "t" : 2,
    "workers" : [ 253, 1 ]
  }, {
    "t" : 4,
    "workers" : [ 142, 253 ]
  }, {
    "t" : 5,
    "workers" : [ 253, 1 ]
  }, {
    "t" : 6,
    "workers" : [ 88, 52 ]
  }, {
    "t" : 7,
    "workers" : [ 142, 253 ]
  } ]
}, {
  "demand" : 6,
  "workerAssignments" : [ {
    "t" : 1,
    "workers" : [ 234 ]
  }, {
    "t" : 2,
    "workers" : [ 14 ]
  }, {
    "t" : 3,
    "workers" : [ 88 ]
  }, {
    "t" : 5,
    "workers" : [ 14 ]
  }, {
    "t" : 6,
    "workers" : [ 14 ]
  } ]
}, {
  "demand" : 7,
  "workerAssignments" : [ {
    "t" : 2,
    "workers" : [ 85, 28, 160 ]
  }, {
    "t" : 3,
    "workers" : [ 269, 52, 216 ]
  }, {
    "t" : 4,
    "workers" : [ 238, 85, 28 ]
  }, {
    "t" : 5,
    "workers" : [ 85, 28, 160 ]
  }, {
    "t" : 6,
    "workers" : [ 269, 42, 78 ]
  }, {
    "t" : 7,
    "workers" : [ 85, 28, 160 ]
  }, {
    "t" : 8,
    "workers" : [ 216, 238, 85 ]
  }, {
    "t" : 9,
    "workers" : [ 269, 52, 85 ]
  } ]
}, {
  "demand" : 8,
  "workerAssignments" : [ {
    "t" : 0,
    "workers" : [ 88, 238, 270, 85 ]
  }, {
    "t" : 1,
    "workers" : [ 238, 270, 78, 85 ]
  }, {
    "t" : 3,
    "workers" : [ 142, 238, 270, 85 ]
  }, {
    "t" : 4,
    "workers" : [ 212, 270, 260, 156 ]
  }, {
    "t" : 5,
    "workers" : [ 212, 270, 260, 156 ]
  }, {
    "t" : 6,
    "workers" : [ 238, 270, 85, 260 ]
  }, {
    "t" : 7,
    "workers" : [ 212, 270, 260, 156 ]
  } ]
}, {
  "demand" : 9,
  "workerAssignments" : [ {
    "t" : 1,
    "workers" : [ 14, 110, 284, 233, 6, 220 ]
  }, {
    "t" : 2,
    "workers" : [ 110, 284, 233, 6, 220, 260 ]
  }, {
    "t" : 3,
    "workers" : [ 14, 110, 284, 233, 6, 220 ]
  }, {
    "t" : 5,
    "workers" : [ 110, 284, 233, 6, 220, 173 ]
  }, {
    "t" : 6,
    "workers" : [ 110, 284, 233, 6, 220, 28 ]
  }, {
    "t" : 8,
    "workers" : [ 14, 110, 284, 233, 6, 220 ]
  } ]
}, {
  "demand" : 10,
  "workerAssignments" : [ {
    "t" : 0,
    "workers" : [ 14, 292, 115 ]
  }, {
    "t" : 1,
    "workers" : [ 28, 288, 0 ]
  }, {
    "t" : 3,
    "workers" : [ 28, 292, 115 ]
  }, {
    "t" : 4,
    "workers" : [ 14, 288, 234 ]
  }, {
    "t" : 8,
    "workers" : [ 28, 292, 115 ]
  }, {
    "t" : 9,
    "workers" : [ 14, 292, 115 ]
  } ]
}, {
  "demand" : 11,
  "workerAssignments" : [ {
    "t" : 0,
    "workers" : [ 260, 28, 156 ]
  }, {
    "t" : 1,
    "workers" : [ 292, 260, 156 ]
  }, {
    "t" : 3,
    "workers" : [ 260, 156, 124 ]
  }, {
    "t" : 4,
    "workers" : [ 292, 124, 173 ]
  }, {
    "t" : 5,
    "workers" : [ 292, 124, 73 ]
  }, {
    "t" : 7,
    "workers" : [ 292, 124, 173 ]
  } ]
}, {
  "demand" : 12,
  "workerAssignments" : [ {
    "t" : 0,
    "workers" : [ 160, 65, 73, 228, 9, 212 ]
  }, {
    "t" : 3,
    "workers" : [ 160, 65, 73, 228, 9, 212 ]
  }, {
    "t" : 4,
    "workers" : [ 160, 65, 73, 228, 9, 41 ]
  }, {
    "t" : 6,
    "workers" : [ 288, 65, 73, 0, 228, 216 ]
  }, {
    "t" : 7,
    "workers" : [ 9, 65, 73, 228, 41, 244 ]
  }, {
    "t" : 8,
    "workers" : [ 160, 65, 73, 228, 9, 212 ]
  }, {
    "t" : 9,
    "workers" : [ 160, 65, 73, 228, 9, 212 ]
  } ]
}, {
  "demand" : 13,
  "workerAssignments" : [ {
    "t" : 0,
    "workers" : [ 38, 184, 189, 253, 6 ]
  }, {
    "t" : 1,
    "workers" : [ 157, 184, 189, 253, 38 ]
  }, {
    "t" : 2,
    "workers" : [ 38, 184, 189, 270, 192 ]
  }, {
    "t" : 5,
    "workers" : [ 38, 184, 189, 192, 169 ]
  }, {
    "t" : 6,
    "workers" : [ 38, 184, 189, 253, 192 ]
  }, {
    "t" : 9,
    "workers" : [ 38, 184, 189, 253, 6 ]
  } ]
}, {
  "demand" : 14,
  "workerAssignments" : [ {
    "t" : 2,
    "workers" : [ 74, 138, 124, 212, 96, 41 ]
  }, {
    "t" : 4,
    "workers" : [ 74, 138, 38, 96, 128, 237 ]
  }, {
    "t" : 5,
    "workers" : [ 74, 138, 96, 41, 128, 237 ]
  }, {
    "t" : 7,
    "workers" : [ 38, 138, 96, 128, 237, 279 ]
  }, {
    "t" : 9,
    "workers" : [ 74, 138, 124, 96, 237, 41 ]
  } ]
}, {
  "demand" : 15,
  "workerAssignments" : [ {
    "t" : 2,
    "workers" : [ 156, 101, 169, 256, 173 ]
  }, {
    "t" : 3,
    "workers" : [ 173, 101, 189, 169, 256 ]
  }, {
    "t" : 5,
    "workers" : [ 244, 101, 256, 2, 266 ]
  }, {
    "t" : 6,
    "workers" : [ 160, 101, 156, 169, 256 ]
  } ]
}, {
  "demand" : 16,
  "workerAssignments" : [ {
    "t" : 0,
    "workers" : [ 297 ]
  }, {
    "t" : 2,
    "workers" : [ 297 ]
  }, {
    "t" : 3,
    "workers" : [ 297 ]
  }, {
    "t" : 4,
    "workers" : [ 189 ]
  }, {
    "t" : 6,
    "workers" : [ 297 ]
  }, {
    "t" : 9,
    "workers" : [ 297 ]
  } ]
}, {
  "demand" : 17,
  "workerAssignments" : [ {
    "t" : 0,
    "workers" : [ 74, 41, 244 ]
  }, {
    "t" : 4,
    "workers" : [ 244, 32, 259 ]
  }, {
    "t" : 5,
    "workers" : [ 228, 32, 259 ]
  }, {
    "t" : 6,
    "workers" : [ 74, 212, 41 ]
  }, {
    "t" : 7,
    "workers" : [ 32, 259, 240 ]
  }, {
    "t" : 8,
    "workers" : [ 74, 38, 41 ]
  }, {
    "t" : 9,
    "workers" : [ 244, 32, 259 ]
  } ]
}, {
  "demand" : 18,
  "workerAssignments" : [ {
    "t" : 0,
    "workers" : [ 289, 265, 233, 201, 220, 137 ]
  }, {
    "t" : 2,
    "workers" : [ 289, 265, 201, 137, 197, 109 ]
  }, {
    "t" : 4,
    "workers" : [ 289, 265, 233, 6, 201, 220 ]
  }, {
    "t" : 6,
    "workers" : [ 289, 265, 201, 137, 197, 109 ]
  }, {
    "t" : 8,
    "workers" : [ 289, 265, 201, 137, 297, 109 ]
  } ]
}, {
  "demand" : 19,
  "workerAssignments" : [ {
    "t" : 0,
    "workers" : [ 21 ]
  }, {
    "t" : 1,
    "workers" : [ 115 ]
  }, {
    "t" : 3,
    "workers" : [ 201 ]
  }, {
    "t" : 4,
    "workers" : [ 115 ]
  }, {
    "t" : 6,
    "workers" : [ 115 ]
  }, {
    "t" : 8,
    "workers" : [ 21 ]
  } ]
}, {
  "demand" : 20,
  "workerAssignments" : [ {
    "t" : 0,
    "workers" : [ 128, 32, 286, 76 ]
  }, {
    "t" : 3,
    "workers" : [ 41, 128, 244, 32 ]
  }, {
    "t" : 4,
    "workers" : [ 286, 76, 240, 130 ]
  }, {
    "t" : 5,
    "workers" : [ 286, 76, 240, 130 ]
  }, {
    "t" : 7,
    "workers" : [ 286, 76, 130, 35 ]
  }, {
    "t" : 8,
    "workers" : [ 286, 128, 32, 76 ]
  }, {
    "t" : 9,
    "workers" : [ 128, 76, 286, 130 ]
  } ]
}, {
  "demand" : 21,
  "workerAssignments" : [ {
    "t" : 0,
    "workers" : [ 173, 2, 166, 45, 59, 230 ]
  }, {
    "t" : 1,
    "workers" : [ 201, 297, 137, 212, 173, 73 ]
  }, {
    "t" : 2,
    "workers" : [ 73, 244, 2, 166, 45, 59 ]
  }, {
    "t" : 3,
    "workers" : [ 137, 2, 166, 45, 59, 230 ]
  }, {
    "t" : 4,
    "workers" : [ 297, 137, 2, 166, 45, 59 ]
  }, {
    "t" : 6,
    "workers" : [ 173, 244, 2, 166, 45, 59 ]
  }, {
    "t" : 8,
    "workers" : [ 173, 244, 2, 166, 45, 59 ]
  } ]
}, {
  "demand" : 22,
  "workerAssignments" : [ {
    "t" : 0,
    "workers" : [ 124, 279, 259 ]
  }, {
    "t" : 1,
    "workers" : [ 124, 244, 166 ]
  }, {
    "t" : 2,
    "workers" : [ 279, 259, 240 ]
  }, {
    "t" : 4,
    "workers" : [ 279, 35, 255 ]
  }, {
    "t" : 6,
    "workers" : [ 124, 279, 259 ]
  }, {
    "t" : 7,
    "workers" : [ 201, 166, 255 ]
  } ]
}, {
  "demand" : 23,
  "workerAssignments" : [ {
    "t" : 0,
    "workers" : [ 240 ]
  }, {
    "t" : 1,
    "workers" : [ 32 ]
  }, {
    "t" : 5,
    "workers" : [ 299 ]
  }, {
    "t" : 6,
    "workers" : [ 32 ]
  }, {
    "t" : 7,
    "workers" : [ 299 ]
  }, {
    "t" : 8,
    "workers" : [ 259 ]
  } ]
}, {
  "demand" : 24,
  "workerAssignments" : [ {
    "t" : 1,
    "workers" : [ 17, 27, 98, 240, 130, 35 ]
  }, {
    "t" : 2,
    "workers" : [ 17, 27, 98, 130, 35, 255 ]
  }, {
    "t" : 3,
    "workers" : [ 17, 27, 98, 240, 130, 35 ]
  }, {
    "t" : 4,
    "workers" : [ 17, 27, 98, 18, 127, 11 ]
  }, {
    "t" : 6,
    "workers" : [ 17, 27, 98, 240, 130, 35 ]
  }, {
    "t" : 7,
    "workers" : [ 17, 27, 98, 18, 127, 11 ]
  }, {
    "t" : 8,
    "workers" : [ 17, 27, 98, 240, 130, 35 ]
  } ]
}, {
  "demand" : 25,
  "workerAssignments" : [ {
    "t" : 0,
    "workers" : [ 130, 35, 255, 127 ]
  }, {
    "t" : 1,
    "workers" : [ 255, 127, 43, 158 ]
  }, {
    "t" : 2,
    "workers" : [ 127, 43, 158, 214 ]
  }, {
    "t" : 3,
    "workers" : [ 255, 127, 43, 158 ]
  }, {
    "t" : 4,
    "workers" : [ 43, 158, 214, 107 ]
  }, {
    "t" : 6,
    "workers" : [ 255, 127, 43, 158 ]
  }, {
    "t" : 7,
    "workers" : [ 43, 158, 214, 107 ]
  }, {
    "t" : 8,
    "workers" : [ 255, 127, 43, 158 ]
  }, {
    "t" : 9,
    "workers" : [ 255, 127, 43, 158 ]
  } ]
}, {
  "demand" : 26,
  "workerAssignments" : [ {
    "t" : 0,
    "workers" : [ 125, 197, 256, 13 ]
  }, {
    "t" : 4,
    "workers" : [ 184, 125, 197, 256 ]
  }, {
    "t" : 6,
    "workers" : [ 125, 9, 13, 237 ]
  }, {
    "t" : 9,
    "workers" : [ 125, 197, 256, 13 ]
  } ]
}, {
  "demand" : 27,
  "workerAssignments" : [ {
    "t" : 1,
    "workers" : [ 59, 45, 2, 118, 204, 66 ]
  }, {
    "t" : 2,
    "workers" : [ 118, 66, 145, 204, 223, 80 ]
  }, {
    "t" : 3,
    "workers" : [ 118, 66, 145, 204, 223, 80 ]
  }, {
    "t" : 5,
    "workers" : [ 17, 45, 59, 118, 204, 27 ]
  }, {
    "t" : 6,
    "workers" : [ 118, 66, 145, 204, 223, 80 ]
  }, {
    "t" : 8,
    "workers" : [ 118, 66, 145, 204, 223, 80 ]
  } ]
}, {
  "demand" : 28,
  "workerAssignments" : [ {
    "t" : 0,
    "workers" : [ 295 ]
  }, {
    "t" : 1,
    "workers" : [ 259 ]
  }, {
    "t" : 2,
    "workers" : [ 295 ]
  }, {
    "t" : 4,
    "workers" : [ 295 ]
  }, {
    "t" : 6,
    "workers" : [ 295 ]
  }, {
    "t" : 7,
    "workers" : [ 295 ]
  }, {
    "t" : 8,
    "workers" : [ 295 ]
  } ]
}, {
  "demand" : 29,
  "workerAssignments" : [ {
    "t" : 0,
    "workers" : [ 69, 121, 266, 205, 161, 180 ]
  }, {
    "t" : 2,
    "workers" : [ 121, 13, 128, 266, 205, 161 ]
  }, {
    "t" : 4,
    "workers" : [ 121, 13, 266, 205, 161, 180 ]
  }, {
    "t" : 5,
    "workers" : [ 289, 121, 265, 13, 205, 161 ]
  }, {
    "t" : 8,
    "workers" : [ 121, 260, 266, 13, 205, 161 ]
  } ]
}, {
  "demand" : 30,
  "workerAssignments" : [ {
    "t" : 0,
    "workers" : [ 66, 223, 182, 43, 158, 214 ]
  }, {
    "t" : 1,
    "workers" : [ 121, 128, 286, 223, 182, 214 ]
  }, {
    "t" : 2,
    "workers" : [ 286, 182, 190, 107, 79, 283 ]
  }, {
    "t" : 3,
    "workers" : [ 121, 286, 182, 214, 190, 107 ]
  }, {
    "t" : 4,
    "workers" : [ 66, 223, 182, 190, 79, 283 ]
  }, {
    "t" : 5,
    "workers" : [ 66, 223, 35, 255, 182, 127 ]
  }, {
    "t" : 8,
    "workers" : [ 190, 182, 100, 214, 79, 107 ]
  }, {
    "t" : 9,
    "workers" : [ 121, 223, 35, 214, 182, 2 ]
  } ]
}, {
  "demand" : 31,
  "workerAssignments" : [ {
    "t" : 0,
    "workers" : [ 284 ]
  }, {
    "t" : 1,
    "workers" : [ 265 ]
  }, {
    "t" : 2,
    "workers" : [ 71 ]
  }, {
    "t" : 5,
    "workers" : [ 279 ]
  }, {
    "t" : 6,
    "workers" : [ 71 ]
  } ]
}, {
  "demand" : 32,
  "workerAssignments" : [ {
    "t" : 1,
    "workers" : [ 279 ]
  }, {
    "t" : 2,
    "workers" : [ 18 ]
  }, {
    "t" : 3,
    "workers" : [ 279 ]
  }, {
    "t" : 4,
    "workers" : [ 67 ]
  }, {
    "t" : 5,
    "workers" : [ 18 ]
  }, {
    "t" : 6,
    "workers" : [ 18 ]
  }, {
    "t" : 7,
    "workers" : [ 67 ]
  } ]
}, {
  "demand" : 33,
  "workerAssignments" : [ {
    "t" : 0,
    "workers" : [ 80, 18 ]
  }, {
    "t" : 1,
    "workers" : [ 80, 18 ]
  }, {
    "t" : 2,
    "workers" : [ 11, 99 ]
  }, {
    "t" : 3,
    "workers" : [ 18, 11 ]
  }, {
    "t" : 6,
    "workers" : [ 11, 99 ]
  }, {
    "t" : 7,
    "workers" : [ 80, 99 ]
  }, {
    "t" : 8,
    "workers" : [ 18, 11 ]
  } ]
}, {
  "demand" : 34,
  "workerAssignments" : [ {
    "t" : 0,
    "workers" : [ 178 ]
  }, {
    "t" : 2,
    "workers" : [ 178 ]
  }, {
    "t" : 3,
    "workers" : [ 178 ]
  }, {
    "t" : 5,
    "workers" : [ 80 ]
  }, {
    "t" : 6,
    "workers" : [ 214 ]
  }, {
    "t" : 7,
    "workers" : [ 178 ]
  }, {
    "t" : 8,
    "workers" : [ 178 ]
  }, {
    "t" : 9,
    "workers" : [ 80 ]
  } ]
}, {
  "demand" : 35,
  "workerAssignments" : [ {
    "t" : 0,
    "workers" : [ 278, 129, 199, 11, 99, 218 ]
  }, {
    "t" : 1,
    "workers" : [ 278, 5, 129, 199, 11, 99 ]
  }, {
    "t" : 2,
    "workers" : [ 278, 129, 199, 218, 55, 131 ]
  }, {
    "t" : 3,
    "workers" : [ 278, 129, 199, 99, 218, 55 ]
  }, {
    "t" : 4,
    "workers" : [ 278, 129, 199, 99, 218, 55 ]
  }, {
    "t" : 7,
    "workers" : [ 278, 129, 199, 182, 218, 55 ]
  }, {
    "t" : 8,
    "workers" : [ 278, 129, 199, 99, 218, 55 ]
  } ]
}, {
  "demand" : 36,
  "workerAssignments" : [ {
    "t" : 0,
    "workers" : [ 97, 44, 95, 16 ]
  }, {
    "t" : 1,
    "workers" : [ 65, 97, 44, 295 ]
  }, {
    "t" : 4,
    "workers" : [ 97, 44, 95, 16 ]
  }, {
    "t" : 7,
    "workers" : [ 97, 44, 95, 16 ]
  }, {
    "t" : 9,
    "workers" : [ 97, 44, 95, 295 ]
  } ]
}, {
  "demand" : 37,
  "workerAssignments" : [ {
    "t" : 0,
    "workers" : [ 217 ]
  }, {
    "t" : 3,
    "workers" : [ 217 ]
  }, {
    "t" : 5,
    "workers" : [ 217 ]
  }, {
    "t" : 9,
    "workers" : [ 217 ]
  } ]
}, {
  "demand" : 38,
  "workerAssignments" : [ {
    "t" : 0,
    "workers" : [ 154, 169, 237, 113, 63 ]
  }, {
    "t" : 2,
    "workers" : [ 154, 237, 113, 63, 95 ]
  }, {
    "t" : 5,
    "workers" : [ 154, 113, 63, 295, 95 ]
  }, {
    "t" : 6,
    "workers" : [ 154, 266, 113, 63, 95 ]
  }, {
    "t" : 7,
    "workers" : [ 154, 169, 266, 113, 63 ]
  } ]
}, {
  "demand" : 39,
  "workerAssignments" : [ {
    "t" : 0,
    "workers" : [ 206, 67, 55 ]
  }, {
    "t" : 1,
    "workers" : [ 206, 169, 67 ]
  }, {
    "t" : 2,
    "workers" : [ 206, 67, 16 ]
  }, {
    "t" : 3,
    "workers" : [ 206, 67, 16 ]
  }, {
    "t" : 7,
    "workers" : [ 206, 8, 262 ]
  } ]
}, {
  "demand" : 40,
  "workerAssignments" : [ {
    "t" : 0,
    "workers" : [ 107 ]
  }, {
    "t" : 1,
    "workers" : [ 107 ]
  }, {
    "t" : 2,
    "workers" : [ 90 ]
  }, {
    "t" : 3,
    "workers" : [ 79 ]
  }, {
    "t" : 4,
    "workers" : [ 178 ]
  }, {
    "t" : 5,
    "workers" : [ 43 ]
  }, {
    "t" : 7,
    "workers" : [ 79 ]
  }, {
    "t" : 8,
    "workers" : [ 90 ]
  }, {
    "t" : 9,
    "workers" : [ 79 ]
  } ]
}, {
  "demand" : 41,
  "workerAssignments" : [ {
    "t" : 1,
    "workers" : [ 190, 196, 95, 183 ]
  }, {
    "t" : 2,
    "workers" : [ 100, 196, 183, 122 ]
  }, {
    "t" : 4,
    "workers" : [ 100, 196, 183, 90 ]
  }, {
    "t" : 5,
    "workers" : [ 158, 196, 214, 190 ]
  }, {
    "t" : 6,
    "workers" : [ 190, 196, 183, 107 ]
  }, {
    "t" : 9,
    "workers" : [ 190, 196, 183, 122 ]
  } ]
}, {
  "demand" : 42,
  "workerAssignments" : [ {
    "t" : 0,
    "workers" : [ 34, 112, 190, 79, 283, 131 ]
  }, {
    "t" : 1,
    "workers" : [ 34, 112, 79, 283, 131, 178 ]
  }, {
    "t" : 3,
    "workers" : [ 34, 112, 283, 131, 90, 100 ]
  }, {
    "t" : 4,
    "workers" : [ 34, 112, 131, 21, 230, 299 ]
  }, {
    "t" : 6,
    "workers" : [ 34, 112, 79, 283, 131, 178 ]
  }, {
    "t" : 8,
    "workers" : [ 34, 112, 283, 131, 230, 299 ]
  }, {
    "t" : 9,
    "workers" : [ 34, 112, 283, 131, 90, 178 ]
  } ]
}, {
  "demand" : 43,
  "workerAssignments" : [ {
    "t" : 1,
    "workers" : [ 109, 165 ]
  }, {
    "t" : 2,
    "workers" : [ 296, 165 ]
  }, {
    "t" : 4,
    "workers" : [ 109, 165 ]
  }, {
    "t" : 6,
    "workers" : [ 296, 165 ]
  }, {
    "t" : 8,
    "workers" : [ 296, 165 ]
  } ]
}, {
  "demand" : 44,
  "workerAssignments" : [ {
    "t" : 0,
    "workers" : [ 100 ]
  }, {
    "t" : 1,
    "workers" : [ 100 ]
  }, {
    "t" : 3,
    "workers" : [ 227 ]
  }, {
    "t" : 4,
    "workers" : [ 94 ]
  }, {
    "t" : 5,
    "workers" : [ 79 ]
  }, {
    "t" : 6,
    "workers" : [ 100 ]
  }, {
    "t" : 7,
    "workers" : [ 100 ]
  }, {
    "t" : 8,
    "workers" : [ 94 ]
  }, {
    "t" : 9,
    "workers" : [ 100 ]
  } ]
}, {
  "demand" : 45,
  "workerAssignments" : [ {
    "t" : 1,
    "workers" : [ 90, 192, 71, 123, 145, 63 ]
  }, {
    "t" : 2,
    "workers" : [ 44, 112, 271, 123, 175, 250 ]
  }, {
    "t" : 4,
    "workers" : [ 154, 175, 71, 271, 145, 250 ]
  }, {
    "t" : 5,
    "workers" : [ 107, 178, 283, 90, 100, 44 ]
  }, {
    "t" : 6,
    "workers" : [ 90, 175, 205, 271, 123, 250 ]
  }, {
    "t" : 8,
    "workers" : [ 44, 192, 271, 123, 175, 63 ]
  }, {
    "t" : 9,
    "workers" : [ 107, 192, 205, 271, 123, 63 ]
  } ]
}, {
  "demand" : 46,
  "workerAssignments" : [ {
    "t" : 0,
    "workers" : [ 183, 192, 239, 126, 94, 200 ]
  }, {
    "t" : 1,
    "workers" : [ 94, 239, 126, 200, 224, 225 ]
  }, {
    "t" : 5,
    "workers" : [ 183, 239, 126, 94, 200, 224 ]
  }, {
    "t" : 6,
    "workers" : [ 94, 239, 126, 200, 225, 12 ]
  }, {
    "t" : 9,
    "workers" : [ 94, 239, 126, 200, 225, 12 ]
  } ]
}, {
  "demand" : 47,
  "workerAssignments" : [ {
    "t" : 0,
    "workers" : [ 71, 251, 167 ]
  }, {
    "t" : 1,
    "workers" : [ 251, 167, 154 ]
  }, {
    "t" : 2,
    "workers" : [ 251, 167, 26 ]
  }, {
    "t" : 4,
    "workers" : [ 251, 167, 26 ]
  }, {
    "t" : 5,
    "workers" : [ 71, 251, 167 ]
  }, {
    "t" : 8,
    "workers" : [ 71, 251, 167 ]
  } ]
}, {
  "demand" : 48,
  "workerAssignments" : [ {
    "t" : 0,
    "workers" : [ 224, 90 ]
  }, {
    "t" : 1,
    "workers" : [ 22, 245 ]
  }, {
    "t" : 2,
    "workers" : [ 224, 239 ]
  }, {
    "t" : 5,
    "workers" : [ 22, 245 ]
  }, {
    "t" : 8,
    "workers" : [ 224, 239 ]
  }, {
    "t" : 9,
    "workers" : [ 224, 245 ]
  } ]
}, {
  "demand" : 49,
  "workerAssignments" : [ {
    "t" : 0,
    "workers" : [ 227, 22, 245, 39 ]
  }, {
    "t" : 1,
    "workers" : [ 16, 218, 227, 191 ]
  }, {
    "t" : 2,
    "workers" : [ 200, 227, 191, 22 ]
  }, {
    "t" : 3,
    "workers" : [ 239, 266, 205, 191 ]
  }, {
    "t" : 5,
    "workers" : [ 67, 11, 99, 218 ]
  }, {
    "t" : 6,
    "workers" : [ 67, 16, 218, 227 ]
  }, {
    "t" : 7,
    "workers" : [ 283, 90, 183, 131 ]
  }, {
    "t" : 9,
    "workers" : [ 16, 22, 191, 39 ]
  } ]
} ]